wython/__init__.py
wython/__main__.py
wython/read.py
wython/transform.py
wython/writein.py
wython/wwritein.py
wython-0.1.1.dist-info/METADATA
wython-0.1.1.dist-info/WHEEL
wython-0.1.1.dist-info/top_level.txt
wython-0.1.1.dist-info/RECORD
