Metadata-Version: 2.1
Name: wython
Version: 0.1.1
Summary: An enhanced version of python (for fun)
Home-page: https://github.com/jiananlan/wython
Author: Jiananlan
Author-email: jal2024@139.com
Classifier: Programming Language :: Python :: 3
Classifier: License :: OSI Approved :: MIT License
Classifier: Operating System :: OS Independent
Requires-Python: >=3.6
Requires-Dist: python-docx
Requires-Dist: Pillow
